{
    "version": "2.0",
    "logging": {
        "applicationInsights": {
            "samplingSettings": {
                "isEnabled": true,
                "excludedTypes": "Request"
            }
        },
        "snapshotConfiguration": {
            "isEnabled": true
        },
        "logLevel": {
            "BerkutBot.Games.Game8.StartCommands.Point10": "Information",
            "BerkutBot.Games.Game8.StartCommands.Point2": "Information",
            "BerkutBot.Games.Game8.StartCommands.Point3": "Information",
            "BerkutBot.Games.Game8.StartCommands.Point4": "Information",
            "BerkutBot.Games.Game8.StartCommands.Point5": "Information",
            "BerkutBot.Games.Game8.StartCommands.Point6": "Information",
            "BerkutBot.Games.Game8.StartCommands.Point7": "Information",
            "BerkutBot.Games.Game8.StartCommands.Point8": "Information",
            "BerkutBot.Games.Game8.StartCommands.Point9": "Information",
            "BerkutBot.Games.Game8.Game8AnswerGo": "Information",
            "BerkutBot.Games.Game8.Game8HelpCommandHandler": "Information",
            "BerkutBot.Games.Game8.Game8StartCommandHandler": "Information"
        }
    }
}